{
  "status": "cached",
  "data": [
    {
      "number": 153,
      "name": "Yogitocat",
      "image": "https://octodex.github.com//images/yogitocat.png",
      "link": "https://octodex.github.com//yogitocat/",
      "authors": [
        {
          "link": "https://github.com/johncreek",
          "image": "https://github.com/johncreek.png"
        }
      ]
    },

    {
      "number": 152,
      "name": "MonatheRivetertocat",
      "image": "https://octodex.github.com//images/mona-the-rivetertocat.png",
      "link": "https://octodex.github.com//mona-the-rivetertocat/",
      "authors": [
        {
          "link": "https://github.com/johncreek",
          "image": "https://github.com/johncreek.png"
        }
      ]
    },

    {
      "number": 151,
      "name": "Manufacturetocat",
      "image": "https://octodex.github.com//images/manufacturetocat.png",
      "link": "https://octodex.github.com//manufacturetocat/",
      "authors": [
        {
          "link": "https://github.com/heyhayhay",
          "image": "https://github.com/heyhayhay.png"
        }
      ]
    },

    {
      "number": 150,
      "name": "OctoAsians",
      "image": "https://octodex.github.com//images/OctoAsians_dex_Full.png",
      "link": "https://octodex.github.com//octoasians/",
      "authors": [
        {
          "link": "https://github.com/cameronfoxly",
          "image": "https://github.com/cameronfoxly.png"
        }
      ]
    },

    {
      "number": 149,
      "name": "Octoqueer",
      "image": "https://octodex.github.com//images/Octoqueer.png",
      "link": "https://octodex.github.com//octoqueer/",
      "authors": [
        {
          "link": "https://github.com/cameronfoxly",
          "image": "https://github.com/cameronfoxly.png"
        }
      ]
    },

    {
      "number": 148,
      "name": "Terracottocat",
      "image": "https://octodex.github.com//images/Terracottocat_Single.png",
      "link": "https://octodex.github.com//terracottocat/",
      "authors": [
        {
          "link": "https://github.com/chubbmo",
          "image": "https://github.com/chubbmo.png"
        }
      ]
    },

    {
      "number": 147,
      "name": "Octogatos",
      "image": "https://octodex.github.com//images/Octogatos.png",
      "link": "https://octodex.github.com//octogatos/",
      "authors": [
        {
          "link": "https://github.com/cameronfoxly",
          "image": "https://github.com/cameronfoxly.png"
        }
      ]
    },

    {
      "number": 146,
      "name": "Adacats",
      "image": "https://octodex.github.com//images/Adacats.png",
      "link": "https://octodex.github.com//adacats/",
      "authors": [
        {
          "link": "https://github.com/cameronfoxly",
          "image": "https://github.com/cameronfoxly.png"
        }
      ]
    },

    {
      "number": 145,
      "name": "Fintechtocat",
      "image": "https://octodex.github.com//images/Fintechtocat.png",
      "link": "https://octodex.github.com//fintechtocat/",
      "authors": [
        {
          "link": "https://github.com/ceciliorz",
          "image": "https://github.com/ceciliorz.png"
        }
      ]
    },

    {
      "number": 144,
      "name": "Brennatocat",
      "image": "https://octodex.github.com//images/Brennatocat.png",
      "link": "https://octodex.github.com//brennatocat/",
      "authors": [
        {
          "link": "https://github.com/johncreek",
          "image": "https://github.com/johncreek.png"
        }
      ]
    },

    {
      "number": 143,
      "name": "Filmtocats",
      "image": "https://octodex.github.com//images/filmtocats.png",
      "link": "https://octodex.github.com//filmtocats/",
      "authors": [
        {
          "link": "https://github.com/heyhayhay",
          "image": "https://github.com/heyhayhay.png"
        }
      ]
    },

    {
      "number": 142,
      "name": "Sentrytocat",
      "image": "https://octodex.github.com//images/Sentrytocat_octodex.jpg",
      "link": "https://octodex.github.com//sentrytocat/",
      "authors": [
        {
          "link": "https://github.com/cameronmcefee",
          "image": "https://github.com/cameronmcefee.png"
        }
      ]
    },

    {
      "number": 141,
      "name": "Umbrellatocat",
      "image": "https://octodex.github.com//images/puddle_jumper_octodex.jpg",
      "link": "https://octodex.github.com//umbrellatocat/",
      "authors": [
        {
          "link": "https://github.com/rubyjazzy",
          "image": "https://github.com/rubyjazzy.png"
        }
      ]
    },

    {
      "number": 140,
      "name": "Boxertocat",
      "image": "https://octodex.github.com//images/boxertocat_octodex.jpg",
      "link": "https://octodex.github.com//boxertocat/",
      "authors": [
        {
          "link": "https://github.com/rubyjazzy",
          "image": "https://github.com/rubyjazzy.png"
        }
      ]
    }
  ]
}
